pdep/__init__.py
pdep/script.py
pdep-0.1.0.dist-info/METADATA
pdep-0.1.0.dist-info/WHEEL
pdep-0.1.0.dist-info/top_level.txt
pdep-0.1.0.dist-info/RECORD
