Metadata-Version: 2.2
Name: Pdep
Version: 0.1.0
Requires-Python: >=3.10
Requires-Dist: requirements-parser>=0.11.0
Requires-Dist: packaging
Requires-Dist: LoggerMan<0.2,>=0.1
Requires-Dist: MDit<0.2,>=0.1
Requires-Dist: PyShellMan<0.2,>=0.1
Requires-Dist: PySyntax<0.2,>=0.1
